fiberoripy/__init__.py
fiberoripy/__main__.py
fiberoripy/aspect_ratios.py
fiberoripy/closures.py
fiberoripy/constants.py
fiberoripy/fit.py
fiberoripy/orientation.py
fiberoripy/tensorplot.py
fiberoripy-1.3.0.dist-info/licenses/LICENSE
fiberoripy-1.3.0.dist-info/METADATA
fiberoripy-1.3.0.dist-info/WHEEL
fiberoripy-1.3.0.dist-info/entry_points.txt
fiberoripy-1.3.0.dist-info/top_level.txt
fiberoripy-1.3.0.dist-info/RECORD
