Metadata-Version: 2.4
Name: fiberoripy
Version: 1.3.0
Summary: Fiber orientation models and closures
Author: Constantin Krauß, Louis Schreyer, Julian Karl Bauer, Johannes Mitsch
Author-email: Nils Meyer <nils.meyer@uni-a.de>
License: MIT License
Project-URL: source, https://github.com/meyer-nils/fiberoripy
Classifier: Programming Language :: Python
Classifier: Programming Language :: Python :: 3
Classifier: Programming Language :: Python :: 3.9
Classifier: Programming Language :: Python :: 3.10
Classifier: Programming Language :: Python :: 3.11
Classifier: Programming Language :: Python :: 3.12
Requires-Python: >=3.9
License-File: LICENSE
Requires-Dist: numpy
Requires-Dist: matplotlib
Requires-Dist: scipy
Requires-Dist: pytest
Requires-Dist: ipympl
Dynamic: license-file
